pysdrweb/__init__.py
pysdrweb/drivers/__init__.py
pysdrweb/drivers/base.py
pysdrweb/drivers/rtl_fm.py
pysdrweb/encoders/__init__.py
pysdrweb/encoders/base.py
pysdrweb/encoders/lame_mp3.py
pysdrweb/encoders/pynative.py
pysdrweb/encoders/soundfile_util.py
pysdrweb/fmserver/__init__.py
pysdrweb/fmserver/context.py
pysdrweb/fmserver/handlers.py
pysdrweb/fmserver/hls_streaming.py
pysdrweb/fmserver/server.py
pysdrweb/util/__init__.py
pysdrweb/util/auth.py
pysdrweb/util/ioloop.py
pysdrweb/util/logger.py
pysdrweb/util/misc.py
pysdrweb_data/__init__.py
pysdrweb_data/index.html
pysdrweb-0.4.1.dist-info/LICENSE
pysdrweb-0.4.1.dist-info/METADATA
pysdrweb-0.4.1.dist-info/WHEEL
pysdrweb-0.4.1.dist-info/entry_points.txt
pysdrweb-0.4.1.dist-info/RECORD
