Metadata-Version: 2.1
Name: pysdrweb
Version: 0.4.1
Summary: Server to host FM Radio via RTL-SDR utilities.
Home-page: https://github.com/eulersIDcrisis/pysdrweb
License: MIT
Author: Aaron Gibson
Author-email: eulersidcrisis@yahoo.com
Requires-Python: >=3.8,<4
Classifier: Development Status :: 3 - Alpha
Classifier: Intended Audience :: Developers
Classifier: Intended Audience :: Telecommunications Industry
Classifier: License :: OSI Approved :: MIT License
Classifier: Operating System :: MacOS :: MacOS X
Classifier: Operating System :: POSIX
Classifier: Programming Language :: Python :: 3
Classifier: Programming Language :: Python :: 3.8
Classifier: Programming Language :: Python :: 3.9
Classifier: Programming Language :: Python :: 3.10
Classifier: Programming Language :: Python :: 3.11
Classifier: Programming Language :: Python :: 3.12
Classifier: Topic :: Communications :: Ham Radio
Classifier: Topic :: Multimedia :: Sound/Audio
Classifier: Topic :: Multimedia :: Sound/Audio :: Players
Provides-Extra: mp3
Requires-Dist: PyYAML (>=6.0,<7.0)
Requires-Dist: click (>=8.0,<8.1)
Requires-Dist: lameenc (>=1.3.1) ; extra == "mp3"
Requires-Dist: soundfile (>=0.10,<1.0)
Requires-Dist: tornado (>=6.1,<7.0)
Project-URL: Bug Tracker, https://github.com/eulersIDcrisis/pysdrweb/issues
Project-URL: Repository, https://github.com/eulersIDcrisis/pysdrweb
